InferenceDF2.py
MainDF2.py
collagen/.DS_Store
collagen/__init__.py
collagen/args_defaults.py
collagen/checkpoints.py
collagen/draw.py
collagen/main.py
collagen/util.py
collagen/apps/.DS_Store
collagen/apps/__init__.py
collagen/apps/easy_app.py.exclude_from_git_for_now
collagen/apps/splits_for_testing.json
collagen/apps/deepfrag/AggregationOperators.py
collagen/apps/deepfrag/README.md.exclude_from_git_for_now
collagen/apps/deepfrag/__init__.py
collagen/apps/deepfrag/defaults.json
collagen/apps/deepfrag/model.py
collagen/apps/deepfrag/model_fusing_modalities.py
collagen/apps/deepfrag/model_paired_data.py
collagen/apps/deepfrag/run.py
collagen/apps/deepfrag/run_example.json
collagen/apps/deepfrag/run_example.sh
collagen/apps/deepfrag/run_multimodal_model.py
collagen/apps/deepfrag/run_pip_test.py
collagen/apps/deepfrag/example_data/5VUP_lig_955.sdf
collagen/apps/deepfrag/example_data/5VUP_prot_955.pdb
collagen/apps/deepfrag/example_data/__init__.py
collagen/core/__init__.py
collagen/core/args.py
collagen/core/debug.py
collagen/core/loader.py
collagen/core/transforms.py.exclude_from_git_for_now
collagen/core/types.py
collagen/core/molecules/__init__.py
collagen/core/molecules/abstract_mol.py
collagen/core/molecules/atom_featurizer.py
collagen/core/molecules/fingerprints.py
collagen/core/molecules/graph_mol.py.exclude_from_git_for_now
collagen/core/molecules/mol.py
collagen/core/molecules/smiles_utils.py
collagen/core/voxelization/__init__.py
collagen/core/voxelization/gen_grid_gpu.py
collagen/core/voxelization/voxelizer.py
collagen/external/.DS_Store
collagen/external/__init__.py
collagen/external/zinc.py.exclude_from_git_for_now
collagen/external/common/__init__.py
collagen/external/common/butina_clustering_split.py
collagen/external/common/cache_filter.py
collagen/external/common/chem_props.py
collagen/external/common/parent_interface.py
collagen/external/common/parent_targets_ligands.py
collagen/external/common/split.py
collagen/external/common/types.py
deepfrag2-2.0.0.dist-info/licenses/LICENSE.md
deepfrag2-2.0.0.dist-info/METADATA
deepfrag2-2.0.0.dist-info/WHEEL
deepfrag2-2.0.0.dist-info/entry_points.txt
deepfrag2-2.0.0.dist-info/top_level.txt
deepfrag2-2.0.0.dist-info/RECORD
