Metadata-Version: 2.4
Name: deepfrag2
Version: 2.0.0
Summary: DeepFrag2: A Deep Learning Framework for Fragment-Based Lead Optimization
Author-email: "Jacob D. Durrant" <durrantj@pitt.edu>
License-Expression: MIT
Project-URL: Homepage, https://durrantlab.pitt.edu/deepfrag2/
Project-URL: Repository, https://github.com/durrantlab/deepfrag2
Classifier: Development Status :: 5 - Production/Stable
Classifier: Intended Audience :: Developers
Classifier: Intended Audience :: Science/Research
Classifier: Programming Language :: Python :: 3
Classifier: Programming Language :: Python :: 3.9
Classifier: Operating System :: OS Independent
Classifier: Topic :: Scientific/Engineering :: Bio-Informatics
Classifier: Topic :: Scientific/Engineering :: Chemistry
Requires-Python: <3.10,>=3.9
License-File: LICENSE.md
Requires-Dist: pip==24.0
Requires-Dist: numpy==1.23.5
Requires-Dist: numba==0.56.4
Requires-Dist: ProDy==2.4.1
Requires-Dist: torch==1.11.0
Requires-Dist: torchvision==0.12.0
Requires-Dist: torchaudio==0.11.0
Requires-Dist: pytorch-lightning==1.4.9
Requires-Dist: scipy==1.11.4
Requires-Dist: pandas==1.4.4
Requires-Dist: rdkit==2024.3.1
Requires-Dist: k3d==2.15.2
Requires-Dist: py3Dmol==2.4.0
Requires-Dist: h5py==3.7.0
Requires-Dist: scikit-learn==1.5.1
Requires-Dist: torchinfo==1.8.0
Requires-Dist: wandb==0.15.8
Requires-Dist: torch_geometric
Requires-Dist: filelock==3.13.1
Requires-Dist: regex
Requires-Dist: sacremoses==0.0.53
Requires-Dist: sentencepiece==0.2.0
Requires-Dist: tokenizers==0.20.0
Requires-Dist: torchmetrics==0.7.3
Requires-Dist: matplotlib==3.8.3
Requires-Dist: protobuf==3.20.3
Requires-Dist: Fancy-aggregations
Requires-Dist: wget
Requires-Dist: fair-esm
Requires-Dist: setuptools<80.9,>=71.0.2
Provides-Extra: dev
Requires-Dist: flake8==4.0.1; extra == "dev"
Requires-Dist: mypy==1.10.0; extra == "dev"
Requires-Dist: pytest==7.1.2; extra == "dev"
Dynamic: license-file
